final_data_crawler_project/__init__.py
final_data_crawler_project/crawler_objects/__init__.py
final_data_crawler_project/crawler_objects/apartment_crawler.py
final_data_crawler_project/crawler_objects/estate_crawler.py
final_data_crawler_project/crawler_objects/house_crawler.py
final_data_crawler_project/crawler_objects/plot_crawler.py
final_data_crawler_project/definitions.py
final_data_crawler_project/main.py
final_data_crawler_project/utils/converters.py
final_data_crawler_project/utils/error_handler.py
final_data_crawler_project-0.1.0.dist-info/LICENSE.txt
final_data_crawler_project-0.1.0.dist-info/METADATA
final_data_crawler_project-0.1.0.dist-info/WHEEL
final_data_crawler_project-0.1.0.dist-info/RECORD
