Metadata-Version: 2.1
Name: final-data-crawler-project
Version: 0.1.0
Summary: 
Author: KM
Author-email: kazimieras.maciekus@gmail.com
Requires-Python: >=3.12,<4.0
Classifier: Programming Language :: Python :: 3
Classifier: Programming Language :: Python :: 3.12
Requires-Dist: openpyxl (>=3.1.2,<4.0.0)
Requires-Dist: pandas (>=2.1.4,<3.0.0)
Requires-Dist: selenium (>=4.16.0,<5.0.0)
